digifi/__init__.py
digifi/corporate_finance/__init__.py
digifi/corporate_finance/capm.py
digifi/corporate_finance/general.py
digifi/financial_instruments/__init__.py
digifi/financial_instruments/bonds.py
digifi/financial_instruments/derivatives.py
digifi/financial_instruments/derivatives_utils.py
digifi/financial_instruments/general.py
digifi/financial_instruments/rates_and_swaps.py
digifi/financial_instruments/stocks.py
digifi/lattice_based_models/__init__.py
digifi/lattice_based_models/binomial_models.py
digifi/lattice_based_models/general.py
digifi/lattice_based_models/trinomial_models.py
digifi/market_making/__init__.py
digifi/market_making/amm.py
digifi/market_making/order_book.py
digifi/portfolio_applications/__init__.py
digifi/portfolio_applications/general.py
digifi/portfolio_applications/portfolio_management.py
digifi/portfolio_applications/portfolio_taxonomy.py
digifi/probability_distributions/__init__.py
digifi/probability_distributions/continuous_probability_distributions.py
digifi/probability_distributions/discrete_probability_distributions.py
digifi/probability_distributions/general.py
digifi/pseudo_random_generators/__init__.py
digifi/pseudo_random_generators/general.py
digifi/pseudo_random_generators/generator_algorithms.py
digifi/pseudo_random_generators/standard_normal_distribution_generators.py
digifi/pseudo_random_generators/uniform_distribution_generators.py
digifi/stochastic_processes/__init__.py
digifi/stochastic_processes/general.py
digifi/stochastic_processes/jump_diffusion_models.py
digifi/stochastic_processes/sde_components.py
digifi/stochastic_processes/sde_components_utils.py
digifi/stochastic_processes/standard_stochastic_models.py
digifi/stochastic_processes/stochastic_drift_components.py
digifi/stochastic_processes/stochastic_volatility_models.py
digifi/technical_indicators/general.py
digifi/technical_indicators/technical_indicators.py
digifi/utilities/__init__.py
digifi/utilities/general_utils.py
digifi/utilities/maths_utils.py
digifi-1.0.4.dist-info/METADATA
digifi-1.0.4.dist-info/WHEEL
digifi-1.0.4.dist-info/licenses/LICENSE
digifi-1.0.4.dist-info/RECORD
