Metadata-Version: 2.1
Name: digifi
Version: 1.0.4
Summary: General-purpose financial library.
Project-URL: Homepage, https://github.com/Digital-Finance-DigiFi/digifi-beta
Project-URL: Bug Tracker, https://github.com/Digital-Finance-DigiFi/digifi-beta/issues
Author: Rem Sadykhov, Berke Muftuoglu
License-File: LICENSE
Classifier: Development Status :: 4 - Beta
Classifier: License :: OSI Approved :: BSD License
Classifier: Natural Language :: English
Classifier: Operating System :: OS Independent
Classifier: Programming Language :: Python :: 3.11
Requires-Python: >=3.11
Requires-Dist: numpy>=1.24
Requires-Dist: scipy>=1.11
